api_limiter/__init__.py
api_limiter/limiter.py
api_limiter/models/config.py
api_limiter/models/limiter.py
api_limiter/storage/in_mmemory.py
api_limiter/storage/protocol.py
api_limiter_py-0.0.6.dist-info/METADATA
api_limiter_py-0.0.6.dist-info/WHEEL
api_limiter_py-0.0.6.dist-info/entry_points.txt
api_limiter_py-0.0.6.dist-info/licenses/LICENSE
api_limiter_py-0.0.6.dist-info/RECORD
