Metadata-Version: 2.1
Name: api-limiter-py
Version: 0.0.6
Summary: Api Limiter
Author-Email: victorgabrieldeon <victordeonroyale@gmail.com>
License: MIT
Requires-Python: >=3.12
